backwork_notifier_sentry-0.2.0.dist-info/METADATA
backwork_notifier_sentry-0.2.0.dist-info/RECORD
backwork_notifier_sentry-0.2.0.dist-info/WHEEL
backwork_notifier_sentry-0.2.0.dist-info/entry_points.txt
backwork_notifier_sentry-0.2.0.dist-info/top_level.txt
sentry/__init__.py
sentry/sentry.py
